databricks_session/__init__.py
databricks_session/databricks_session.py
databricks_session-0.3.0.dist-info/LICENSE
databricks_session-0.3.0.dist-info/METADATA
databricks_session-0.3.0.dist-info/WHEEL
databricks_session-0.3.0.dist-info/RECORD
