Metadata-Version: 2.1
Name: databricks-session
Version: 0.3.0
Summary: A simple util to get a spark and mlflow session objects from an .env file
License: MIT
Author: Carlos D. Escobar-Valbuena
Author-email: carlosdavidescobar@gmail.com
Requires-Python: >=3.9,<4.0
Classifier: License :: OSI Approved :: MIT License
Classifier: Programming Language :: Python :: 3
Classifier: Programming Language :: Python :: 3.9
Classifier: Programming Language :: Python :: 3.10
Classifier: Programming Language :: Python :: 3.11
Classifier: Programming Language :: Python :: 3.12
Requires-Dist: databricks-connect (>=13.1.0,<14.0.0)
Requires-Dist: databricks-sql-connector (>=2.7.0,<3.0.0)
Requires-Dist: mlflow (>=2.4.1,<3.0.0)
Requires-Dist: pydantic (>=1.10.9,<2.0.0)
Requires-Dist: python-dotenv (>=1.0.0,<2.0.0)
Requires-Dist: typing-extensions (>=4.7.0,<5.0.0)
